lbcapi/__init__.py
lbcapi/api.py
lbcapi-1.0.3.dist-info/LICENSE
lbcapi-1.0.3.dist-info/METADATA
lbcapi-1.0.3.dist-info/WHEEL
lbcapi-1.0.3.dist-info/top_level.txt
lbcapi-1.0.3.dist-info/RECORD
